streamlit_js_eval/__init__.py
streamlit_js_eval/index.html
streamlit_js_eval/__pycache__/__init__.cpython-311.pyc
streamlit_js_eval_no_logs-0.1.8.dist-info/LICENSE
streamlit_js_eval_no_logs-0.1.8.dist-info/METADATA
streamlit_js_eval_no_logs-0.1.8.dist-info/WHEEL
streamlit_js_eval_no_logs-0.1.8.dist-info/top_level.txt
streamlit_js_eval_no_logs-0.1.8.dist-info/RECORD
