Metadata-Version: 2.1
Name: streamlit-js-eval-no-logs
Version: 0.1.8
Summary: A custom Streamlit component to evaluate arbitrary Javascript expressions.
Home-page: https://github.com/aghasemi/streamlit_js_eval_no_log
Author: ['Alireza Ghasemi', 'Fabian Lucas']
Author-email: ['ghasemi.a.ir@gmail.com', 'fl@msr.de']
Keywords: Python,Streamlit,JavaScript
Requires-Python: >=3.8
License-File: LICENSE
Requires-Dist: streamlit>=1.0.0
